datascience_pacakge/__init__.py
chady-0.2.dist-info/METADATA
chady-0.2.dist-info/WHEEL
chady-0.2.dist-info/top_level.txt
chady-0.2.dist-info/RECORD
